{
  "version": "1.2.20",
  "version_full": "1.2.20.20250107005",
  "release_date": "2026-01-07",
  "build_number": "20250107005",
  "download_url": "downloads/URTM_DizinTarama_Client_v1.2.20.zip",
  "file_size": "70KB",
  "changelog": [
    "v1.2.20 - 2025-10-07:",
    "- KRITIK: Montaj dosya yolu kaydetme sorununu gidermek için detaylı INFO logları eklendi",
    "- GELİŞTİRME: Backend ve Client'ta sldasm_yolu transferi izlenebilir hale getirildi",
    "",
    "v1.2.19 - 2025-10-07:",
    "- KRITIK: Parça-detay penceresinde montaj dosyaları görüntülenme sorunu düzeltildi",
    "- KRITIK: combine_part_data fonksiyonunda yanlış anahtar isimleri düzeltildi (_files suffix)",
    "- KRITIK: Parçalar için hasAssembly alanı hesaplanmıyordu - düzeltildi",
    "- YENİ: Parçaların aynı isimli montaj dosyaları ile ilişkilendirilmesi",
    "- GELİŞTİRME: select_assemblies fonksiyonuna detaylı debug logging eklendi",
    "",
    "v1.2.18 - 2025-10-07:",
    "- YENİ: Tarama sonuçlarında Montaj (.sldasm) sütunu eklendi",
    "- KRITIK: Montaj dosyalarının görüntülenmemesi sorunu düzeltildi",
    "",
    "v1.2.17 - 2025-10-07:",
    "- YENİ: .sldasm montaj dosyaları (.sldasm) desteği eklendi",
    "- YENİ: Montajları Seç (🔧) filtre butonu eklendi",
    "- YENİ: Backend'de sldasm_yolu alanı eklendi",
    "- KRITIK: PDF dosyası (teknik_resim_path) kaydetme sorunu düzeltildi",
    "- GELİŞTİRME: Parça detay penceresinde montaj dosyaları gösterimi",
    "- GELİŞTİRME: Dosya yolu kaydetme sistemi iyileştirildi",
    "",
    "v1.2.16 - 2025-10-07:",
    "- KRITIK: Backend API URL'si port 3000'e düzeltildi",
    "- YENİ: Parça detay penceresinde veritabanına kaydetme butonu eklendi",
    "- YENİ: Seçili parçaları toplu olarak veritabanına kaydetme özelliği",
    "- YENİ: Database client'a save_parts_to_database fonksiyonu eklendi",
    "- GELİŞTİRME: Kaydetme sonuçlarını detaylı gösterim",
    "- GELİŞTİRME: Progress indicator ve onay dialog'lari",
    "",
    "v1.2.14 - 2025-01-06:",
    "- YENİ: Parça detay penceresinde veritabanına kaydetme butonu eklendi",
    "- YENİ: Seçili parçaları toplu olarak veritabanına kaydetme özelliği",
    "- YENİ: Database client'a save_parts_to_database fonksiyonu eklendi",
    "",
    "v1.2.13 - 2025-01-06:",
    "- KRITIK: Parça seçim limiti 100'den 1.000.000'a çıkarıldı",
    "- KRITIK: Backend API limitleri güncellendi",
    "- GELİŞTİRME: Büyük ölçekli dizin tarama desteği",
    "",
    "v1.2.12 - 2025-10-03:",
    "- KRITIK: Lambda closure sorunu düzeltildi (buton karışması)",
    "- KRITIK: Her buton kendi dosyasını doğru şekilde açar",
    "- GELİŞTİRME: Lambda default value kullanıldı",
    "",
    "v1.2.11 - 2025-10-03:",
    "- KRITIK: CAD dosya anahtar adları düzeltildi",
    "- KRITIK: Yanlış anahtar isimleri düzeltildi (sldprt→sldprt_files)",
    "- KRITIK: Image loading unpack hatası düzeltildi",
    "- YENİ: Doğru veri yapısı ile CAD dosyaları artık gösterilecek",
    "",
    "v1.2.10 - 2025-10-03:",
    "- KRITIK: UI queue hatası düzeltildi (ValueError: too many values to unpack)",
    "- GELİŞTİRME: Queue processing daha güvenli hale getirildi",
    "- GELİŞTİRME: DEBUG level log'lar INFO seviyesine çekildi",
    "- YENİ: Part data keys ve file listesi artık log'da görünür",
    "",
    "v1.2.9 - 2025-10-03:",
    "- GELİŞTİRME: Kapsamlı debug logging eklendi",
    "- GELİŞTİRME: CAD dosya veri yapısı analizi için log'lar",
    "- KRITIK: Part data keys ve file listesi kontrolü",
    "- YENİ: Detaylı debug mesajları ile sorun tespiti",
    "",
    "v1.2.8 - 2025-10-03:",
    "- KRITIK: CAD dosya butonları görünmeme sorunu düzeltildi",
    "- GELİŞTİRME: Lambda closure sorunları çözüldü",
    "- GELİŞTİRME: Butonlar daha belirgin hale getirildi (padding artırıldı)",
    "- YENİ: Hand cursor ve hover background efektleri",
    "",
    "v1.2.7 - 2025-10-03:",
    "- YENİ: CAD dosyaları için tıklanabilir dosya yolu linkleri",
    "- YENİ: .sldprt ve .slddrw dosyaları doğrudan açılabilir",
    "- YENİ: Link stili ile kullanıcı dostu dosya gösterimi",
    "- GELİŞTİRME: Dosya linkleri için hover efektleri ve altı çizili stil",
    "",
    "v1.2.6 - 2025-10-03:",
    "- YENİ: 2 saniye gecikmeli otomatik resim yükleme özelliği",
    "- YENİ: Sayfa açıldıktan sonra resimler otomatik yüklenir",
    "- GELİŞTİRME: Auto-load mekanizması ile kullanıcı deneyimi iyileştirildi",
    "",
    "v1.2.5 - 2025-10-03:",
    "- KRITIK: İlk açılışta resim yükleme sorunu düzeltildi",
    "- YENİ: Enhanced image loading with direct label tracking",
    "- YENİ: Cache'den resimleri hemen gösterme özelliği",
    "- GELİŞTİRME: Thread-safe image widget referans yönetimi",
    "",
    "v1.2.4 - 2025-10-03:",
    "- KRITIK: ttk.Label height sorunu düzeltildi",
    "- KRITIK: GUI crash hatası giderildi",
    "- YENİ: Frame-based image placeholder sistemi",
    "- GELİŞTİRME: PIL/Pillow kurulum script'i eklendi",
    "",
    "v1.2.3 - 2025-10-03:",
    "- YENİ: Parça detay penceresinde görsel gösterim özelliği",
    "- YENİ: Otomatik resim yükleme ve görüntüleme",
    "- GELİŞTİRME: Parça kartlarında entegre görseller",
    "- GELİŞTİRME: İmage display component'i güncellendi",
    "",
    "v1.2.2 - 2025-09-26:",
    "- KRITIK: Parça resim ve teknik resim görünmeme sorunu düzeltildi",
    "- YENİ: Server image path'leri web tarayıcısında açılma özelliği",
    "- GELİŞTİRME: Image URL helper fonksiyonu eklendi",
    "- GELİŞTİRME: Web browser integration for database images",
    "",
    "v1.2.1 - 2025-09-26:",
    "- KRITIK: TreeView güncelleme hatası düzeltildi (dict->string conversion)",
    "- KRITIK: Parça detay formu veri geçiş sorunu çözüldü (parcaAdi eksikliği)",
    "- KRITIK: Backend SQLite ILIKE syntax hatası düzeltildi",
    "- GELİŞTİRME: missingFields API response formatı düzeltildi",
    "- GELİŞTİRME: Selection manager veri yapısı iyileştirildi",
    "",
    "v1.2.0 - 2025-09-24:",
    "- MAJOR: Checkbox parca secim sistemi eklendi",
    "- MAJOR: Database entegrasyonu ve parca detay penceresi",
    "- YENİ: Scrollable parca kartlari goruntuleme",
    "- YENİ: Real-time database durum gosterimi",
    "- YENİ: Toplu parca secim kontrolleri",
    "- YENİ: Durum bazli filtreleme (tam/kismi/eksik)",
    "- YENİ: Selection istatistikleri ve callback sistemi",
    "- YENİ: Asenkron veri yukleme ve thread-safe UI",
    "- YENİ: 3 yeni Python modulu (database_client, selection_manager, part_detail_window)",
    "- GELİŞTİRME: TreeView checkbox kolonu entegrasyonu",
    "- GELİŞTİRME: Backend API genişletildi (3 yeni endpoint)",
    "- GELİŞTİRME: Hata yonetimi ve graceful degradation",
    "",
    "v1.1.1 - 2024-12-23:",
    "- KRITIK: Batch dosya encoding sorunu cozuldu",
    "- Yeni basit kurulum scriptleri eklendi",
    "- REM komutu yerine :: kullanildi",
    "- Encoding test scripti eklendi",
    "",
    "v1.1.0 - 2024-12-23:",
    "- Turkce karakter sorunu cozuldu",
    "- requirements.txt sorunu duzeltildi",
    "- Yeni kurulum scriptleri eklendi",
    "- Hata kontrolu gelistirildi",
    "- Debug modlari eklendi",
    "",
    "v1.0.0 - 2024-12-22:",
    "- Ilk surum",
    "- Temel dizin tarama ozelligi",
    "- Windows uyumlulugu",
    "- Sunucu iletisimi"
  ],
  "requirements": [
    "Python 3.8+",
    "Windows 10/11",
    "requests>=2.25.0"
  ],
  "compatible_backend": "11.3.184+"
}